dkdc_todo/__init__.py
dkdc_todo/main.py
dkdc_todo/ui/cli.py
dkdc_todo/ui/gui/__init__.py
dkdc_todo/ui/gui/main.py
dkdc_todo/ui/gui/todos.py
dkdc_todo-0.0.5.dist-info/METADATA
dkdc_todo-0.0.5.dist-info/WHEEL
dkdc_todo-0.0.5.dist-info/entry_points.txt
dkdc_todo-0.0.5.dist-info/top_level.txt
dkdc_todo-0.0.5.dist-info/RECORD
