Metadata-Version: 2.1
Name: dkdc-todo
Version: 0.0.5
Summary: todo
Author-email: Cody <cody@dkdc.dev>
Project-URL: Homepage, https://github.com/dkdc-io/dkdc-todo
Project-URL: Bug Tracker, https://github.com/dkdc-io/dkdc-todo/issues
Classifier: Programming Language :: Python :: 3
Classifier: License :: OSI Approved :: MIT License
Classifier: Operating System :: OS Independent
Requires-Python: >=3.12
Requires-Dist: dkdc-state
Requires-Dist: dkdc-util
Provides-Extra: dev
Requires-Dist: ruff; extra == "dev"
Requires-Dist: ipython; extra == "dev"
Requires-Dist: jupyter; extra == "dev"
Requires-Dist: nbclient; extra == "dev"
Requires-Dist: ipykernel; extra == "dev"
Provides-Extra: test
Requires-Dist: pytest; extra == "test"
Provides-Extra: ui
Requires-Dist: typer; extra == "ui"
Requires-Dist: shiny; extra == "ui"
Requires-Dist: shinyswatch; extra == "ui"
Requires-Dist: shinywidgets; extra == "ui"
Requires-Dist: plotly; extra == "ui"
